hotools/__init__.py
hotools/data_structure.py
hotools/graph.py
hotools/image_binder.py
hotools/json_tools.py
hotools/pillow_tools.py
hotools/transform.py
htools/__init__.py
htools/data_structure.py
htools/graph.py
htools/image_binder.py
htools/json_tools.py
htools/pillow_tools.py
htools/transform.py
hotools-0.1.1.dist-info/LICENSE
hotools-0.1.1.dist-info/METADATA
hotools-0.1.1.dist-info/WHEEL
hotools-0.1.1.dist-info/top_level.txt
hotools-0.1.1.dist-info/RECORD
