Metadata-Version: 2.1
Name: hotools
Version: 0.1.1
Summary: hotools: Tools for Python made by Hosoi.
Home-page: https://github.com/hosson/hotools
Author: HOSOI Hiroyuki
Author-email: hosoi0410@gmail.com
Maintainer: HOSOI Hiroyuki
Maintainer-email: hosoi0410@gmail.com
License: MIT
Download-URL: https://github.com/hosson/hotools
Keywords: tool
Platform: UNKNOWN
Classifier: License :: OSI Approved :: MIT License
Classifier: Programming Language :: Python :: 3.8
License-File: LICENSE
